token_generator/border.png
token_generator/main.py
token_generator-1.0.0.dist-info/METADATA
token_generator-1.0.0.dist-info/WHEEL
token_generator-1.0.0.dist-info/entry_points.txt
token_generator-1.0.0.dist-info/RECORD
