Metadata-Version: 2.1
Name: token-generator
Version: 1.0.0
Summary: 
Author: Joao Pedro Watson
Author-email: joaopedrowatson@hotmail.com
Requires-Python: >=3.8,<=3.11
Classifier: Programming Language :: Python :: 3
Classifier: Programming Language :: Python :: 3.8
Classifier: Programming Language :: Python :: 3.9
Classifier: Programming Language :: Python :: 3.10
Classifier: Programming Language :: Python :: 3.11
Requires-Dist: blue (>=0.9.1,<0.10.0)
Requires-Dist: isort (>=5.12.0,<6.0.0)
Requires-Dist: pillow (>=10.0.0,<11.0.0)
Requires-Dist: rembg (>=2.0.50,<3.0.0)
Requires-Dist: typer[all] (>=0.9.0,<0.10.0)
